django_directory_api/__init__.py
django_directory_api/admin.py
django_directory_api/apps.py
django_directory_api/auth.py
django_directory_api/checks.py
django_directory_api/models.py
django_directory_api/management/__init__.py
django_directory_api/management/commands/__init__.py
django_directory_api/management/commands/api_discover.py
django_directory_api/migrations/0001_initial.py
django_directory_api/migrations/__init__.py
django_directory_api/schemas/__init__.py
django_directory_api/schemas/common.py
django_directory_api-0.1.1.dist-info/METADATA
django_directory_api-0.1.1.dist-info/WHEEL
django_directory_api-0.1.1.dist-info/licenses/LICENSE
django_directory_api-0.1.1.dist-info/RECORD
